tsty/__init__.py
tsty/cli.py
tsty/utils/__init__.py
tsty/utils/apple.py
tsty/utils/common.py
tsty-0.0.5.3.dist-info/METADATA
tsty-0.0.5.3.dist-info/WHEEL
tsty-0.0.5.3.dist-info/entry_points.txt
tsty-0.0.5.3.dist-info/top_level.txt
tsty-0.0.5.3.dist-info/RECORD
